README.txt
setup.py
docs/HISTORY.txt
docs/INSTALL.txt
docs/LICENSE.GPL
docs/LICENSE.txt
docs/TODO.txt
plone/__init__.py
plone.checksum.egg-info/PKG-INFO
plone.checksum.egg-info/SOURCES.txt
plone.checksum.egg-info/dependency_links.txt
plone.checksum.egg-info/entry_points.txt
plone.checksum.egg-info/namespace_packages.txt
plone.checksum.egg-info/not-zip-safe
plone.checksum.egg-info/requires.txt
plone.checksum.egg-info/top_level.txt
plone/checksum/BlobFile.txt
plone/checksum/README.txt
plone/checksum/__init__.py
plone/checksum/at.py
plone/checksum/configure.zcml
plone/checksum/interfaces.py
plone/checksum/tests.py
plone/checksum/version.txt
plone/checksum/browser/CMFEditions.txt
plone/checksum/browser/README.txt
plone/checksum/browser/__init__.py
plone/checksum/browser/configure.zcml
