Metadata-Version: 1.0
Name: plone.checksum
Version: 0.1
Summary: Checksums for ZODB
Home-page: http://svn.plone.org/svn/collective/plone.checksum
Author: Jazkarta
Author-email: team@jazkarta.com
License: GPL
Keywords: zodb zope integrity
Platform: UNKNOWN
Classifier: Intended Audience :: Developers
Classifier: Framework :: Plone
Classifier: Framework :: Zope2
Classifier: Programming Language :: Python
Classifier: Topic :: Software Development :: Libraries :: Python Modules
